markdownfeedgenerator/Gatherer.py
markdownfeedgenerator/MarkdownFile.py
markdownfeedgenerator/__init__.py
markdownfeedgenerator/Exceptions/__init__.py
markdownfeedgenerator/Generators/__init__.py
markdownfeedgenerator/Generators/Default/DefaultFeedGenerator.py
markdownfeedgenerator/Generators/Default/Exceptions/__init__.py
markdownfeedgenerator/Generators/Default/Models/Feed.py
markdownfeedgenerator/Generators/Default/Models/FeedItem.py
markdownfeedgenerator/Generators/Default/Models/__init__.py
markdownfeedgenerator/Generators/Html/HtmlFeedGenerator.py
markdownfeedgenerator/Generators/Html/template.html
markdownfeedgenerator/Generators/Json/JsonFeedGenerator.py
markdownfeedgenerator/Generators/Json/Models/Author.py
markdownfeedgenerator/Generators/Json/Models/Hub.py
markdownfeedgenerator/Generators/Json/Models/JsonFeed.py
markdownfeedgenerator/Generators/Json/Models/JsonFeedItem.py
markdownfeedgenerator/Generators/Json/Models/__init__.py
markdownfeedgenerator-2.8.4.dist-info/LICENSE
markdownfeedgenerator-2.8.4.dist-info/METADATA
markdownfeedgenerator-2.8.4.dist-info/WHEEL
markdownfeedgenerator-2.8.4.dist-info/top_level.txt
markdownfeedgenerator-2.8.4.dist-info/RECORD
