Metadata-Version: 2.1
Name: markdownfeedgenerator
Version: 2.8.4
Summary: Small library that can generated paged feeds (json, html, etc) based on a collection of markdown files.
Author-email: Scott Straughan <dev@null.com>
Project-URL: Homepage, https://github.com/scottstraughan/markdownfeedgenerator
Project-URL: Issues, https://github.com/scottstraughan/markdownfeedgenerator/issues
Classifier: Programming Language :: Python :: 3
Classifier: License :: OSI Approved :: MIT License
Classifier: Operating System :: OS Independent
Requires-Python: >=3.11.0
License-File: LICENSE
Requires-Dist: pyyaml
Requires-Dist: python-dateutil
Requires-Dist: markdown
Requires-Dist: html2text
Requires-Dist: chevron
Requires-Dist: requests
